odoo/addons/l10n_ro_stock_price_difference/README.rst
odoo/addons/l10n_ro_stock_price_difference/__init__.py
odoo/addons/l10n_ro_stock_price_difference/__manifest__.py
odoo/addons/l10n_ro_stock_price_difference/i18n/l10n_ro_stock_price_difference.pot
odoo/addons/l10n_ro_stock_price_difference/i18n/ro.po
odoo/addons/l10n_ro_stock_price_difference/migrations/14.0.5.10.1/pre-migration.py
odoo/addons/l10n_ro_stock_price_difference/migrations/14.0.5.6.1/pre-migration.py
odoo/addons/l10n_ro_stock_price_difference/models/__init__.py
odoo/addons/l10n_ro_stock_price_difference/models/account_move.py
odoo/addons/l10n_ro_stock_price_difference/models/account_move_line.py
odoo/addons/l10n_ro_stock_price_difference/models/stock_landed_cost.py
odoo/addons/l10n_ro_stock_price_difference/readme/CONTRIBUTORS.rst
odoo/addons/l10n_ro_stock_price_difference/readme/DESCRIPTION.rst
odoo/addons/l10n_ro_stock_price_difference/security/ir.model.access.csv
odoo/addons/l10n_ro_stock_price_difference/static/description/icon.png
odoo/addons/l10n_ro_stock_price_difference/static/description/index.html
odoo/addons/l10n_ro_stock_price_difference/tests/__init__.py
odoo/addons/l10n_ro_stock_price_difference/tests/common.py
odoo/addons/l10n_ro_stock_price_difference/tests/test_purchase.py
odoo/addons/l10n_ro_stock_price_difference/tests/test_purchase_dozen.py
odoo/addons/l10n_ro_stock_price_difference/tests/test_purchase_refund.py
odoo/addons/l10n_ro_stock_price_difference/tests/test_sale.py
odoo/addons/l10n_ro_stock_price_difference/wizard/__init__.py
odoo/addons/l10n_ro_stock_price_difference/wizard/price_difference_confirmation.py
odoo/addons/l10n_ro_stock_price_difference/wizard/price_difference_confirmation.xml
odoo14_addon_l10n_ro_stock_price_difference-14.0.5.14.0.dist-info/METADATA
odoo14_addon_l10n_ro_stock_price_difference-14.0.5.14.0.dist-info/WHEEL
odoo14_addon_l10n_ro_stock_price_difference-14.0.5.14.0.dist-info/top_level.txt
odoo14_addon_l10n_ro_stock_price_difference-14.0.5.14.0.dist-info/RECORD
