Metadata-Version: 2.1
Name: odoo14-addon-l10n-ro-stock-price-difference
Version: 14.0.5.14.0
Summary: Romania - Stock Accounting Price Difference
Home-page: https://github.com/OCA/l10n-romania
Author: NextERP Romania,Dorin Hongu,Odoo Community Association (OCA)
Author-email: support@odoo-community.org
License: AGPL-3
Platform: UNKNOWN
Classifier: Programming Language :: Python
Classifier: Framework :: Odoo
Classifier: Framework :: Odoo :: 14.0
Classifier: License :: OSI Approved :: GNU Affero General Public License v3
Classifier: Development Status :: 6 - Mature
Requires-Python: >=3.6
Requires-Dist: odoo14-addon-l10n-ro-stock-account-notice
Requires-Dist: odoo <14.1dev,>=14.0a
